[
{
    "model": "general_settings.websitesetting",
    "pk": 1,
    "fields": {
        "site": 1,
        "tagline": "Trosgate Marketplace",
        "description": "This is the Trosgate Marketplace",
        "site_Logo": "site/logo.png",
        "address": null,
        "created_at": "2023-05-19T21:28:13.890Z",
        "modified": "2023-05-19T21:28:13.898Z",
        "proposal_detail": false,
        "category_type": false,
        "project_type": false,
        "banner_type": "false",
        "title_block": "Hire Experts or Team",
        "subtitle_block": "Consectetur adipisicing elit sed dotem eiusmod tempor incuntes ut labore etdolore maigna aliqua enim.",
        "video_title": "See For Yourself!",
        "video_description": "Hire Experts or Team",
        "video_url": null,
        "banner_image": "",
        "banner_color": "purple",
        "banner_button_one_color": "green",
        "banner_button_two_color": "light",
        "promo_type": "1",
        "promo_title": "#1 Choice For Businesses",
        "promo_subtitle": "Business on the Go",
        "promo_description": "The Example Marketplace",
        "promo_image": "freelancer/awards/banner.png",
        "footer_description": "Dotem eiusmod tempor incune utnaem labore etdolore maigna aliqua enim poskina ilukita ylokem lokateise ination voluptate velit esse cillum dolore eu fugiat nulla pariatur lokaim urianewce",
        "button_color": "purple",
        "navbar_color": "purple",
        "twitter_url": "https://twitter.com",
        "instagram_url": "https://instagram.com",
        "youtube_url": "https://youtube.com",
        "facebook_url": "https://facebook.com",
        "brand_ambassador_image": "site/Trosgate/home_promo_JqJTMqr.jpg",
        "announcement": null,
        "protocol": "http://"
    }
},
{
    "model": "general_settings.storagebuckets",
    "pk": 1,
    "fields": {
        "description": "Local Storage and Amazon S3 Configuration",
        "bucket_name": null,
        "access_key": null,
        "secret_key": null,
        "storage_type": true
    }
},
{
    "model": "general_settings.testemail",
    "pk": 1,
    "fields": {
        "title": "Testing Email",
        "test_email": "tester@gmail.com"
    }
},
{
    "model": "general_settings.autologoutsystem",
    "pk": 1,
    "fields": {
        "preview": "Auto Logout System",
        "warning_time_schedule": 2,
        "interval": "+2 Hours"
    }
},
{
    "model": "general_settings.subscriptiongateway",
    "pk": 1,
    "fields": {
        "name": "This is the switch for controlling the subscriptions appearing to customer",
        "paypal": true,
        "stripe": true,
        "razorpay": true,
        "flutterwave": true
    }
},
{
    "model": "general_settings.depositgateway",
    "pk": 1,
    "fields": {
        "name": "This is the switch for controlling the deposit appearing to customer",
        "paypal": true,
        "stripe": true,
        "razorpay": true,
        "flutterwave": false
    }
},
{
    "model": "general_settings.category",
    "pk": 1,
    "fields": {
        "name": "Graphic and Design",
        "icon": "categories/img-05_L2fQUYL.jpg",
        "preview": "This is the preview of the category",
        "visible": true,
        "slug": "graphic-and-design"
    }
},
{
    "model": "general_settings.category",
    "pk": 2,
    "fields": {
        "name": "Social Media Marketing",
        "icon": "categories/img-04_7d5k17f.png",
        "preview": "This is the preview of the category",
        "visible": true,
        "slug": "social-media-marketing"
    }
},
{
    "model": "general_settings.category",
    "pk": 3,
    "fields": {
        "name": "Academics and Research",
        "icon": "categories/category.png",
        "preview": "This is the preview of the category",
        "visible": true,
        "slug": "academics-and-research"
    }
},
{
    "model": "general_settings.category",
    "pk": 4,
    "fields": {
        "name": "Network and IT",
        "icon": "categories/category.png",
        "preview": "This is the preview of the category",
        "visible": true,
        "slug": "network-and-it"
    }
},
{
    "model": "general_settings.category",
    "pk": 5,
    "fields": {
        "name": "Engineering",
        "icon": "categories/img-01_VNb5Wa9.png",
        "preview": "This is the preview of the category",
        "visible": true,
        "slug": "engineering"
    }
},
{
    "model": "general_settings.category",
    "pk": 6,
    "fields": {
        "name": "Web Development",
        "icon": "categories/img-05_hRDDTVU.png",
        "preview": "This is the preview of the category",
        "visible": true,
        "slug": "web-development"
    }
},
{
    "model": "general_settings.category",
    "pk": 7,
    "fields": {
        "name": "Mobile App Development",
        "icon": "categories/img-10_Pb3ezvz.png",
        "preview": "This is the preview of the category",
        "visible": true,
        "slug": "mobile-app-development"
    }
},
{
    "model": "general_settings.category",
    "pk": 8,
    "fields": {
        "name": "Audio and Video",
        "icon": "categories/img-03_hhaSwT5.png",
        "preview": "This is the preview of the category",
        "visible": true,
        "slug": "audio-and-videos"
    }
},
{
    "model": "general_settings.department",
    "pk": 1,
    "fields": {
        "name": "Sales and Marketing"
    }
},
{
    "model": "general_settings.department",
    "pk": 2,
    "fields": {
        "name": "Ecommerce"
    }
},
{
    "model": "general_settings.department",
    "pk": 3,
    "fields": {
        "name": "Social Media"
    }
},
{
    "model": "general_settings.department",
    "pk": 4,
    "fields": {
        "name": "Graphic and Design"
    }
},
{
    "model": "general_settings.department",
    "pk": 5,
    "fields": {
        "name": "Web and Tech"
    }
},
{
    "model": "general_settings.department",
    "pk": 6,
    "fields": {
        "name": "Human Relations"
    }
},
{
    "model": "general_settings.department",
    "pk": 7,
    "fields": {
        "name": "Public Relations"
    }
},
{
    "model": "general_settings.size",
    "pk": 1,
    "fields": {
        "size": "1 - 9 Staffs"
    }
},
{
    "model": "general_settings.size",
    "pk": 2,
    "fields": {
        "size": "10 - 49 Staffs"
    }
},
{
    "model": "general_settings.size",
    "pk": 3,
    "fields": {
        "size": "50 - 99 Staffs"
    }
},
{
    "model": "general_settings.size",
    "pk": 4,
    "fields": {
        "size": "100 - 499 Staffs"
    }
},
{
    "model": "general_settings.size",
    "pk": 5,
    "fields": {
        "size": "500 - 1000 Staffs"
    }
},
{
    "model": "general_settings.size",
    "pk": 6,
    "fields": {
        "size": "Above 1000"
    }
},
{
    "model": "general_settings.skill",
    "pk": 1,
    "fields": {
        "name": "htmx"
    }
},
{
    "model": "general_settings.skill",
    "pk": 2,
    "fields": {
        "name": "html"
    }
},
{
    "model": "general_settings.skill",
    "pk": 3,
    "fields": {
        "name": "proof-reading"
    }
},
{
    "model": "general_settings.skill",
    "pk": 4,
    "fields": {
        "name": "accounting"
    }
},
{
    "model": "general_settings.skill",
    "pk": 5,
    "fields": {
        "name": "poetry"
    }
},
{
    "model": "general_settings.skill",
    "pk": 6,
    "fields": {
        "name": "cash management"
    }
},
{
    "model": "general_settings.skill",
    "pk": 7,
    "fields": {
        "name": "p.r.o"
    }
},
{
    "model": "general_settings.skill",
    "pk": 8,
    "fields": {
        "name": "tech writing"
    }
},
{
    "model": "general_settings.skill",
    "pk": 9,
    "fields": {
        "name": "graphic design"
    }
},
{
    "model": "general_settings.skill",
    "pk": 10,
    "fields": {
        "name": "type-writer"
    }
},
{
    "model": "general_settings.skill",
    "pk": 11,
    "fields": {
        "name": "django"
    }
},
{
    "model": "general_settings.skill",
    "pk": 12,
    "fields": {
        "name": "python"
    }
},
{
    "model": "general_settings.skill",
    "pk": 13,
    "fields": {
        "name": "php"
    }
},
{
    "model": "general_settings.skill",
    "pk": 14,
    "fields": {
        "name": "mongodb"
    }
},
{
    "model": "general_settings.skill",
    "pk": 15,
    "fields": {
        "name": "docker"
    }
},
{
    "model": "general_settings.skill",
    "pk": 16,
    "fields": {
        "name": "java"
    }
},
{
    "model": "general_settings.skill",
    "pk": 17,
    "fields": {
        "name": "javascript"
    }
},
{
    "model": "general_settings.skill",
    "pk": 18,
    "fields": {
        "name": "mobile app"
    }
},
{
    "model": "general_settings.skill",
    "pk": 19,
    "fields": {
        "name": "blogging"
    }
},
{
    "model": "general_settings.skill",
    "pk": 20,
    "fields": {
        "name": "sculpture"
    }
},
{
    "model": "general_settings.skill",
    "pk": 21,
    "fields": {
        "name": "engineering"
    }
},
{
    "model": "general_settings.skill",
    "pk": 22,
    "fields": {
        "name": "music"
    }
},
{
    "model": "general_settings.skill",
    "pk": 23,
    "fields": {
        "name": "video content"
    }
},
{
    "model": "general_settings.skill",
    "pk": 24,
    "fields": {
        "name": "voiceover"
    }
},
{
    "model": "general_settings.skill",
    "pk": 25,
    "fields": {
        "name": "business plan"
    }
},
{
    "model": "general_settings.skill",
    "pk": 26,
    "fields": {
        "name": "book writing"
    }
},
{
    "model": "general_settings.skill",
    "pk": 27,
    "fields": {
        "name": "ebook"
    }
},
{
    "model": "general_settings.skill",
    "pk": 28,
    "fields": {
        "name": "transcript"
    }
},
{
    "model": "general_settings.skill",
    "pk": 29,
    "fields": {
        "name": "postgresql"
    }
},
{
    "model": "general_settings.skill",
    "pk": 30,
    "fields": {
        "name": "mysql"
    }
},
{
    "model": "general_settings.proposalguides",
    "pk": 1,
    "fields": {
        "guide": "Beware of prices that appear too good to be true",
        "status": true
    }
},
{
    "model": "general_settings.proposalguides",
    "pk": 2,
    "fields": {
        "guide": "If possible, chat the user and confirm the order details",
        "status": true
    }
},
{
    "model": "general_settings.proposalguides",
    "pk": 3,
    "fields": {
        "guide": "Contact support if you notice suspicious action on this service",
        "status": true
    }
},
{
    "model": "general_settings.discountsystem",
    "pk": 1,
    "fields": {
        "preview": "Level Based Discount System",
        "level_one_name": "Level One Discount System",
        "level_one_rate": 0,
        "level_one_start_amount": 10,
        "level_one_delta_amount": 110,
        "level_two_name": "Level Two Discount System",
        "level_two_rate": 0,
        "level_two_start_amount": 111,
        "level_two_delta_amount": 499,
        "level_three_name": "Level Three Discount System",
        "level_three_rate": 0,
        "level_three_start_amount": 500,
        "level_three_delta_amount": 999,
        "level_four_name": "Level Three Discount System",
        "level_four_rate": 0,
        "level_four_start_amount": 1000
    }
},
{
    "model": "general_settings.hiringfee",
    "pk": 1,
    "fields": {
        "preview": "Freelancer fees and charges",
        "extcontract_fee_percentage": 20,
        "contract_fee_percentage": 20,
        "contract_fee_extra": 5,
        "contract_delta_amount": 350,
        "proposal_fee_percentage": 20,
        "proposal_fee_extra": 5,
        "proposal_delta_amount": 350,
        "application_fee_percentage": 20,
        "application_fee_extra": 5,
        "application_delta_amount": 300
    }
},
{
    "model": "general_settings.exachangerateapi",
    "pk": 1,
    "fields": {
        "preview": "Exchange rate API",
        "exchange_rates_api_key": "6801286373207985c087f61d",
        "status": true
    }
},
{
    "model": "general_settings.paymentscontrol",
    "pk": 1,
    "fields": {
        "preview": "All about Transfer and Withdrawal configuration",
        "min_balance": 0,
        "max_receiver_balance": 1500,
        "min_transfer": 20,
        "max_transfer": 500,
        "min_withdrawal": 20,
        "max_withdrawal": 500
    }
},
{
    "model": "general_settings.depositcontrol",
    "pk": 1,
    "fields": {
        "preview": "All about Deposit configuration",
        "min_balance": 0,
        "max_balance": 2000,
        "min_deposit": 20,
        "max_deposit": 500
    }
},
{
    "model": "general_settings.payday",
    "pk": 1,
    "fields": {
        "preview": "Payday Timelines that users should expect money",
        "payday_converter": "three_days"
    }
},
{
    "model": "general_settings.mailer",
    "pk": 1,
    "fields": {
        "email_hosting_server": "smtp-relay.brevo.com",
        "email_hosting_server_password": "1dWKrEc3kQfRYbSD",
        "email_hosting_username": "myvoistudio@gmail.com",
        "from_email": "myvoistudio@gmail.com",
        "email_use_tls": true,
        "email_use_ssl": false,
        "email_fail_silently": true,
        "email_hosting_server_port": 587,
        "email_timeout": 60
    }
}
]
